sc2players/__init__.py
sc2players/__main__.py
sc2players/__version__.py
sc2players/cli.py
sc2players/constants.py
sc2players/playerManagement.py
sc2players/playerPreGame.py
sc2players/playerRecord.py
sc2players/dataPlayers/player_blizzbot1_veryeasy.json
sc2players/dataPlayers/player_blizzbot2_easy.json
sc2players/dataPlayers/player_blizzbot3_medium.json
sc2players/dataPlayers/player_blizzbot4_mediumhard.json
sc2players/dataPlayers/player_blizzbot5_hard.json
sc2players/dataPlayers/player_blizzbot6_harder.json
sc2players/dataPlayers/player_blizzbot7_veryhard.json
sc2players/dataPlayers/player_blizzbotx_cheat1.json
sc2players/dataPlayers/player_blizzbotx_cheat2.json
sc2players/dataPlayers/player_blizzbotx_cheat3.json
sc2players/dataPlayers/player_defaulthuman.json
sc2players/dataPlayers/player_efishandsee.json
sc2players/dataPlayers/player_mapexplorer.json
sc2players/dataPlayers/player_test.json
sc2players-0.4.0.dist-info/METADATA
sc2players-0.4.0.dist-info/RECORD
sc2players-0.4.0.dist-info/WHEEL
sc2players-0.4.0.dist-info/entry_points.txt
sc2players-0.4.0.dist-info/top_level.txt
