Metadata-Version: 2.1
Name: sc2players
Version: 0.4.0
Summary: A suystem of managing Starcraft 2 player profiles.
Home-page: https://github.com/ttinies/sc2players
Author: Versentiedge LLC
Author-email: help.fool@versentiedge.com
License: Apache License 2.0
Platform: UNKNOWN
Classifier: License :: OSI Approved :: Apache Software License
Classifier: Programming Language :: Python
Classifier: Programming Language :: Python :: 3
Classifier: Programming Language :: Python :: 3.6
Classifier: Programming Language :: Python :: Implementation :: CPython
Classifier: Programming Language :: Python :: Implementation :: PyPy
Classifier: Topic :: Games/Entertainment :: Real Time Strategy
Classifier: Topic :: Scientific/Engineering :: Artificial Intelligence
Requires-Python: >3.4
Requires-Dist: sc2common
Requires-Dist: six
